dtx_apis_prompts_utils/__init__.py
dtx_apis_prompts_utils/prompt.py
dtx_apis_prompts_utils-0.2.1.dist-info/METADATA
dtx_apis_prompts_utils-0.2.1.dist-info/WHEEL
dtx_apis_prompts_utils-0.2.1.dist-info/RECORD
