Metadata-Version: 2.3
Name: dtx-apis-prompts-utils
Version: 0.2.1
Summary: Detoxio APIs Prompts parsing and processing utils
Author: jchauhan
Author-email: jitendra@detoxio.ai
Requires-Python: >=3.10,<4.0
Classifier: Programming Language :: Python :: 3
Classifier: Programming Language :: Python :: 3.10
Classifier: Programming Language :: Python :: 3.11
Classifier: Programming Language :: Python :: 3.12
Classifier: Programming Language :: Python :: 3.13
Requires-Dist: protobuf (>=3.20.3)
Requires-Dist: pydantic (>=2.10.4,<3.0.0)
